local_references_mcp/__init__.py
local_references_mcp/main.py
local_references_mcp/references.py
local_references_mcp-0.5.2.dist-info/METADATA
local_references_mcp-0.5.2.dist-info/WHEEL
local_references_mcp-0.5.2.dist-info/entry_points.txt
local_references_mcp-0.5.2.dist-info/licenses/LICENSE
local_references_mcp-0.5.2.dist-info/RECORD
