Metadata-Version: 2.4
Name: local-references-mcp
Version: 0.5.2
Summary: Offer documentation in your local filesystem as references via mcp tools
License-File: LICENSE
Requires-Python: >=3.12
Requires-Dist: asyncclick>=8.1.8
Requires-Dist: fastmcp>=2.3.5
Requires-Dist: mcp>=1.9.0
Requires-Dist: pydantic>=2.11.4
Requires-Dist: syrupy>=4.9.1
